paras-2.0.0.dist-info/licenses/LICENSE.txt
parasect/__init__.py
parasect/api.py
parasect/cli_paras.py
parasect/cli_parasect.py
parasect/version.py
parasect/core/__init__.py
parasect/core/chem.py
parasect/core/constants.py
parasect/core/domain.py
parasect/core/featurisation.py
parasect/core/genbank.py
parasect/core/github.py
parasect/core/helpers.py
parasect/core/hmmer.py
parasect/core/muscle.py
parasect/core/parasect_result.py
parasect/core/parsing.py
parasect/core/pca.py
parasect/core/tabular.py
parasect/core/taxonomy.py
parasect/core/writers.py
parasect/data/AMP-binding_full.hmm
parasect/data/AMP-binding_full.hmm.h3f
parasect/data/AMP-binding_full.hmm.h3i
parasect/data/AMP-binding_full.hmm.h3m
parasect/data/AMP-binding_full.hmm.h3p
parasect/data/AMP-binding_hmmer2.hmm
parasect/data/__init__.py
parasect/data/active_site.txt
parasect/data/active_site_hmm2.txt
parasect/data/fingerprints.txt
parasect/data/fingerprints_bacterial.txt
parasect/data/hashes.txt
parasect/data/included_substrates.txt
parasect/data/included_substrates_bacterial.txt
parasect/data/physicochemical_properties.txt
parasect/data/stachelhaus.txt
parasect/data/stachelhaus_hmm2.txt
parasect/data/structure_alignment.fasta
parasect/data/database_files/domain_substrate_mapping.txt
parasect/data/database_files/domains.fasta
parasect/data/database_files/extended_signatures.fasta
parasect/data/database_files/parasect_dataset.txt
parasect/data/database_files/proteins.fasta
parasect/data/database_files/signatures.fasta
parasect/data/database_files/smiles.tsv
parasect/data/database_files/taxonomy.txt
parasect/data/database_files/signature_positions/positions.txt
parasect/data/database_files/signature_positions/relative_positions.txt
parasect/database/__init__.py
parasect/database/add_user_submissions.py
parasect/database/build_database.py
parasect/database/extract_signature_positions.py
parasect/database/flatfiles_from_db.py
parasect/database/get_substrate_mapping.py
parasect/database/populate_database.py
paras-2.0.0.dist-info/METADATA
paras-2.0.0.dist-info/WHEEL
paras-2.0.0.dist-info/entry_points.txt
paras-2.0.0.dist-info/top_level.txt
paras-2.0.0.dist-info/RECORD
