Metadata-Version: 2.4
Name: paras
Version: 2.0.0
Summary: Predictive algorithm for resolving A-domain specificity featurising enzyme and compound in tandem.
Home-page: https://github.com/BTheDragonMaster/parasect
Author: Barbara Terlouw
Author-email: barbara.terlouw@wur.nl
Maintainer: David Meijer
Maintainer-email: david.meijer@wur.nl
Keywords: paras,parasect,non-ribosomal peptide,substrate specificity,prediction
Classifier: Development Status :: 1 - Planning
Classifier: Environment :: Console
Classifier: Intended Audience :: Developers
Classifier: License :: OSI Approved :: MIT License
Classifier: Operating System :: OS Independent
Classifier: Framework :: Pytest
Classifier: Framework :: tox
Classifier: Framework :: Sphinx
Classifier: Programming Language :: Python
Classifier: Programming Language :: Python :: 3.9
Classifier: Programming Language :: Python :: 3 :: Only
Requires-Python: >=3.9
License-File: LICENSE.txt
Requires-Dist: scipy
Requires-Dist: biopython
Requires-Dist: joblib
Requires-Dist: pikachu-chem
Requires-Dist: numpy==1.23.0
Requires-Dist: scikit-learn==1.2.0
Requires-Dist: ncbi-acc-download>=0.2.5
Requires-Dist: sqlalchemy
Requires-Dist: iterative-stratification==0.1.9
Requires-Dist: imblearn
Requires-Dist: pandas
Requires-Dist: seaborn
Provides-Extra: tests
Requires-Dist: coverage; extra == "tests"
Requires-Dist: pytest; extra == "tests"
Requires-Dist: tox; extra == "tests"
Dynamic: license-file
